pandas_flow/__init__.py
pandas_flow/cytoscape_renderer.py
pandas_flow/events.py
pandas_flow/html_histogram.py
pandas_flow/interceptors.py
pandas_flow/mermaid_renderer.py
pandas_flow/stats.py
pandas_flow/tracker.py
pandas_flow/visualization.py
pandas_flow/imgs/healthcare_pipeline.png
pandas_flow/imgs/logo.jpg
pandas_flow/imgs/modern.png
pandas_flowchart-0.3.1.dist-info/METADATA
pandas_flowchart-0.3.1.dist-info/WHEEL
pandas_flowchart-0.3.1.dist-info/licenses/LICENSE
pandas_flowchart-0.3.1.dist-info/RECORD
