Metadata-Version: 2.4
Name: pandas-flowchart
Version: 0.3.1
Summary: A library for tracking pandas operations and generating HTML or Mermaid flowcharts
Project-URL: Homepage, https://github.com/yourusername/pandas-flowchart
Project-URL: Documentation, https://github.com/yourusername/pandas-flowchart#readme
Project-URL: Repository, https://github.com/yourusername/pandas-flowchart
Project-URL: Issues, https://github.com/yourusername/pandas-flowchart/issues
Author: rafael scherer
License: MIT
License-File: LICENSE
Keywords: data-pipeline,flowchart,mermaid,pandas,visualization
Classifier: Development Status :: 4 - Beta
Classifier: Intended Audience :: Developers
Classifier: Intended Audience :: Science/Research
Classifier: License :: OSI Approved :: MIT License
Classifier: Programming Language :: Python :: 3
Classifier: Programming Language :: Python :: 3.11
Classifier: Programming Language :: Python :: 3.12
Classifier: Topic :: Scientific/Engineering :: Visualization
Classifier: Topic :: Software Development :: Libraries :: Python Modules
Requires-Python: >=3.11
Requires-Dist: build>=1.3.0
Requires-Dist: ipykernel>=7.1.0
Requires-Dist: matplotlib>=3.8.0
Requires-Dist: numpy>=1.24.0
Requires-Dist: pandas>=2.0.0
Requires-Dist: seaborn>=0.13.0
Requires-Dist: twine>=6.2.0
Provides-Extra: all
Requires-Dist: mypy>=1.0.0; extra == 'all'
Requires-Dist: pandas-stubs>=2.0.0; extra == 'all'
Requires-Dist: playwright>=1.40.0; extra == 'all'
Requires-Dist: pytest-cov>=4.0.0; extra == 'all'
Requires-Dist: pytest>=7.0.0; extra == 'all'
Requires-Dist: ruff>=0.1.0; extra == 'all'
Provides-Extra: dev
Requires-Dist: mypy>=1.0.0; extra == 'dev'
Requires-Dist: pandas-stubs>=2.0.0; extra == 'dev'
Requires-Dist: pytest-cov>=4.0.0; extra == 'dev'
Requires-Dist: pytest>=7.0.0; extra == 'dev'
Requires-Dist: ruff>=0.1.0; extra == 'dev'
Provides-Extra: png
Requires-Dist: playwright>=1.40.0; extra == 'png'
